digitalarzengine/__init__.py
digitalarzengine/main.py
digitalarzengine/manage.py
digitalarzengine/proj_bootstrap.py
digitalarzengine/settings.py
digitalarzengine/analysis/__init__.py
digitalarzengine/analysis/meteo_analysis.py
digitalarzengine/analysis/rainfall/__init__.py
digitalarzengine/analysis/rainfall/rainfall_analysis.py
digitalarzengine/analysis/runoff/__init__.py
digitalarzengine/analysis/runoff/runoff_accumulation.py
digitalarzengine/analysis/runoff/runoff_coefficient.py
digitalarzengine/analysis/soil/__init__.py
digitalarzengine/analysis/soil/soil_capacity_analysis.py
digitalarzengine/analysis/terrain/__init__.py
digitalarzengine/analysis/terrain/terain_hydro_analysis.py
digitalarzengine/io/__init__.py
digitalarzengine/io/cog_raster.py
digitalarzengine/io/file_io.py
digitalarzengine/io/rio_raster.py
digitalarzengine/io/gee/__init__.py
digitalarzengine/io/gee/gee_auth.py
digitalarzengine/io/gee/gee_image.py
digitalarzengine/io/gee/gee_image_collection.py
digitalarzengine/io/gee/gee_region.py
digitalarzengine/io/gee/gpd_vector.py
digitalarzengine/io/managers/__init__.py
digitalarzengine/io/managers/data_manager.py
digitalarzengine/io/managers/db_manager.py
digitalarzengine/io/managers/s3_manager.py
digitalarzengine/pipeline/__init__.py
digitalarzengine/pipeline/gee_pipeline.py
digitalarzengine/pipeline/pak_data.py
digitalarzengine/processing/__init__.py
digitalarzengine/processing/operations/__init__.py
digitalarzengine/processing/operations/geodesy_ops.py
digitalarzengine/processing/operations/transformation_ops.py
digitalarzengine/processing/raster/__init__.py
digitalarzengine/processing/raster/band_process.py
digitalarzengine/processing/raster/rio_process.py
digitalarzengine/scripts/__init__.py
digitalarzengine/scripts/snow_cover.py
digitalarzengine/scripts/water/__init__.py
digitalarzengine/scripts/water/jrc_monthly.py
digitalarzengine/utils/__init__.py
digitalarzengine/utils/crypto.py
digitalarzengine/utils/date_utils.py
digitalarzengine-0.4.14.dist-info/METADATA
digitalarzengine-0.4.14.dist-info/WHEEL
digitalarzengine-0.4.14.dist-info/top_level.txt
digitalarzengine-0.4.14.dist-info/RECORD
