Metadata-Version: 2.4
Name: digitalarzengine
Version: 0.4.14
Summary: DigitalArzEngine for GEE, raster and vector data processing
Author: Ather Ashraf
Author-email: atherashraf@gmail.com
Keywords: raster,vector,digital earth engine
Classifier: Development Status :: 3 - Alpha
Classifier: Intended Audience :: Developers
Classifier: Programming Language :: Python :: 3
Classifier: Operating System :: OS Independent
Requires-Python: >=3.7
Dynamic: author
Dynamic: author-email
Dynamic: classifier
Dynamic: description
Dynamic: description-content-type
Dynamic: keywords
Dynamic: requires-python
Dynamic: summary
